scidllab/__init__.py
scidllab/ex1.py
scidllab/ex2.py
scidllab/ex3.py
scidllab/ex3a.py
scidllab/ex4.py
scidllab/ex5.py
scidllab-0.1.0.dist-info/METADATA
scidllab-0.1.0.dist-info/WHEEL
scidllab-0.1.0.dist-info/top_level.txt
scidllab-0.1.0.dist-info/RECORD
